{
    "teamDataList": [
        {
            "id": 1,
            "name": "德玛西亚",
            "schoolId": 1,
            "playerDataList": [
                {
                    "id": 1001,
                    "name": "张三",
                    "gender": "男"
                },
                {
                    "id": 1003,
                    "name": "李四",
                    "gender": "女"
                }
            ],
            "recordDataList": null
        },
        {
            "id": 2,
            "name": "啦啦啦",
            "schoolId": 1,
            "playerDataList": [
                {
                    "id": 1002,
                    "name": "阿三",
                    "gender": "男"
                },
                {
                    "id": 1004,
                    "name": "阿四",
                    "gender": "女"
                }
            ],
            "recordDataList": null
        }
    ],
    "questionMap": {
        "1": "你来发明",
        "2": "牛顿摆"
    },
    "schoolMap": {
        "1": "南京大学",
        "2": "北京大学"
    }
}